uge/__init__.py
uge/api/__init__.py
uge/api/ar_api.py
uge/api/qconf_api.py
uge/api/impl/__init__.py
uge/api/impl/access_list_manager.py
uge/api/impl/admin_host_manager.py
uge/api/impl/ar_manager.py
uge/api/impl/calendar_manager.py
uge/api/impl/checkpointing_environment_manager.py
uge/api/impl/cluster_configuration_manager.py
uge/api/impl/cluster_queue_manager.py
uge/api/impl/complex_configuration_manager.py
uge/api/impl/dict_based_object_manager.py
uge/api/impl/dict_list_based_object_manager.py
uge/api/impl/execution_host_manager.py
uge/api/impl/host_group_manager.py
uge/api/impl/job_class_manager.py
uge/api/impl/list_based_object_manager.py
uge/api/impl/manager_manager.py
uge/api/impl/operator_manager.py
uge/api/impl/parallel_environment_manager.py
uge/api/impl/project_manager.py
uge/api/impl/qconf_executor.py
uge/api/impl/qrdel_executor.py
uge/api/impl/qrstat_executor.py
uge/api/impl/qrsub_executor.py
uge/api/impl/resource_quota_set_manager.py
uge/api/impl/scheduler_configuration_manager.py
uge/api/impl/share_tree_manager.py
uge/api/impl/submit_host_manager.py
uge/api/impl/user_manager.py
uge/cli/__init__.py
uge/cli/qconf_cli.py
uge/cli/qconf_convert.py
uge/config/__init__.py
uge/config/config_manager.py
uge/constants/__init__.py
uge/constants/uge_status.py
uge/exceptions/__init__.py
uge/exceptions/ar_exception.py
uge/exceptions/authorization_error.py
uge/exceptions/command_failed.py
uge/exceptions/configuration_error.py
uge/exceptions/invalid_argument.py
uge/exceptions/invalid_request.py
uge/exceptions/object_already_exists.py
uge/exceptions/object_not_found.py
uge/exceptions/qconf_exception.py
uge/exceptions/qmaster_unreachable.py
uge/log/__init__.py
uge/log/log_manager.py
uge/log/logger_factory.py
uge/log/stream_log_handler.py
uge/log/timed_rotating_file_log_handler.py
uge/log/trace_log_record.py
uge/log/trace_logger.py
uge/objects/__init__.py
uge/objects/access_list_v1_0.py
uge/objects/advance_reservation_v1_0.py
uge/objects/ar_object_factory.py
uge_pycl-8.11.0.dist-info/LICENSE
uge_pycl-8.11.0.dist-info/METADATA
uge_pycl-8.11.0.dist-info/WHEEL
uge_pycl-8.11.0.dist-info/entry_points.txt
uge_pycl-8.11.0.dist-info/top_level.txt
uge_pycl-8.11.0.dist-info/RECORD
