Metadata-Version: 2.1
Name: uge-pycl
Version: 8.11.0
Summary: UGE Python Configuration Library
Home-page: https://www.altair.com
Author: Altair Engineering Inc.
Author-email: support@altair.com
License: Apache 2.0
Platform: Posix; MacOS X
Classifier: Intended Audience :: Developers
Classifier: Operating System :: OS Independent
Classifier: Programming Language :: Python :: 2
Classifier: Programming Language :: Python :: 2.6
Classifier: Programming Language :: Python :: 2.7
Classifier: Programming Language :: Python :: 3
Requires-Dist: decorator
Requires-Dist: xmltodict
